{
	"feature": "fokastudio:global/stalactite_2",
	"placement": [
		{
			"type": "minecraft:block_predicate_filter",
			"predicate": {
				"type": "minecraft:matching_block_tag",
				"offset": [
					0,
					1,
					0
				],
				"tag": "fokastudio:stalactites_replacable"
			}
		},
		{
			"type": "minecraft:count",
			"count": {
				"type": "minecraft:weighted_list",
				"distribution": [
					{
						"weight": 100,
						"data": 7
					},
					{
						"weight": 50,
						"data": 14
					},
					{
						"weight": 25,
						"data": 28
					},
					{
						"weight": 1,
						"data": 40
					}
				]
			}
		},
		{
			"type": "minecraft:in_square"
		},
		{
			"type": "minecraft:height_range",
			"height": {
				"type": "minecraft:uniform",
				"min_inclusive": {
					"above_bottom": 0
				},
				"max_inclusive": {
					"absolute": 256
				}
			}
		},
		{
			"type": "minecraft:environment_scan",
			"direction_of_search": "up",
			"max_steps": 32,
			"target_condition": {
				"type": "minecraft:has_sturdy_face",
				"direction": "down"
			},
			"allowed_search_condition": {
				"type": "minecraft:matching_blocks",
				"blocks": [
					"minecraft:air"
				]
			}
		},
		{
			"type": "minecraft:random_offset",
			"xz_spread": 0,
			"y_spread": -1
		},
		{
			"type": "minecraft:biome"
		},
		{
			"type": "minecraft:noise_based_count",
			"noise_to_count_ratio": 12,
			"noise_factor": 55,
			"noise_offset": 0
		}
	]
}
